nationalparks_v1/__init__.py
nationalparks_v1/data/__init__.py
nationalparks_v1/data/activities.csv
nationalparks_v1/data/parks_list.csv
nationalparks_v1/nationalparks_v1.py
nationalparks_v1-2.0.5.dist-info/LICENSE
nationalparks_v1-2.0.5.dist-info/WHEEL
nationalparks_v1-2.0.5.dist-info/METADATA
nationalparks_v1-2.0.5.dist-info/RECORD
